LICENSE.md
MANIFEST.in
README.md
pyproject.toml
setup.cfg
setup.py
lib/hts_engine_API/src/CMakeLists.txt
lib/hts_engine_API/src/COPYING
lib/hts_engine_API/src/README
lib/hts_engine_API/src/hts_engine_API.pc.in
lib/hts_engine_API/src/bin/hts_engine.c
lib/hts_engine_API/src/include/HTS_engine.h
lib/hts_engine_API/src/lib/HTS_audio.c
lib/hts_engine_API/src/lib/HTS_engine.c
lib/hts_engine_API/src/lib/HTS_gstream.c
lib/hts_engine_API/src/lib/HTS_hidden.h
lib/hts_engine_API/src/lib/HTS_label.c
lib/hts_engine_API/src/lib/HTS_misc.c
lib/hts_engine_API/src/lib/HTS_model.c
lib/hts_engine_API/src/lib/HTS_pstream.c
lib/hts_engine_API/src/lib/HTS_sstream.c
lib/hts_engine_API/src/lib/HTS_vocoder.c
lib/open_jtalk/src/CMakeLists.txt
lib/open_jtalk/src/COPYING
lib/open_jtalk/src/README
lib/open_jtalk/src/bin/open_jtalk.c
lib/open_jtalk/src/build/CMakeFiles/3.18.2/CompilerIdC/CMakeCCompilerId.c
lib/open_jtalk/src/build/CMakeFiles/3.18.2/CompilerIdCXX/CMakeCXXCompilerId.cpp
lib/open_jtalk/src/build/CMakeFiles/CheckIncludeFiles/HAVE_CTYPE_H.c
lib/open_jtalk/src/build/CMakeFiles/CheckIncludeFiles/HAVE_DIRENT_H.c
lib/open_jtalk/src/build/CMakeFiles/CheckIncludeFiles/HAVE_FCNTL_H.c
lib/open_jtalk/src/build/CMakeFiles/CheckIncludeFiles/HAVE_INTTYPES_H.c
lib/open_jtalk/src/build/CMakeFiles/CheckIncludeFiles/HAVE_IO_H.c
lib/open_jtalk/src/build/CMakeFiles/CheckIncludeFiles/HAVE_MEMORY_H.c
lib/open_jtalk/src/build/CMakeFiles/CheckIncludeFiles/HAVE_SETJMP_H.c
lib/open_jtalk/src/build/CMakeFiles/CheckIncludeFiles/HAVE_STDINT_H.c
lib/open_jtalk/src/build/CMakeFiles/CheckIncludeFiles/HAVE_STDLIB_H.c
lib/open_jtalk/src/build/CMakeFiles/CheckIncludeFiles/HAVE_STRINGS_H.c
lib/open_jtalk/src/build/CMakeFiles/CheckIncludeFiles/HAVE_STRING_H.c
lib/open_jtalk/src/build/CMakeFiles/CheckIncludeFiles/HAVE_SYS_MMAN_H.c
lib/open_jtalk/src/build/CMakeFiles/CheckIncludeFiles/HAVE_SYS_STAT_H.c
lib/open_jtalk/src/build/CMakeFiles/CheckIncludeFiles/HAVE_SYS_TIMES_H.c
pyopenjtalk.egg-info/PKG-INFO
pyopenjtalk.egg-info/SOURCES.txt
pyopenjtalk.egg-info/dependency_links.txt
pyopenjtalk.egg-info/requires.txt
pyopenjtalk.egg-info/top_level.txt
