Metadata-Version: 2.1
Name: pyopenjtalk
Version: 0.3.2
Summary: A python wrapper for OpenJTalk
Home-page: https://github.com/r9y9/pyopenjtalk
Author: Ryuichi Yamamoto
Author-email: zryuichi@gmail.com
License: MIT
Keywords: OpenJTalk,Research
Classifier: Operating System :: POSIX
Classifier: Operating System :: Unix
Classifier: Operating System :: MacOS
Classifier: Operating System :: Microsoft :: Windows
Classifier: Programming Language :: Cython
Classifier: Programming Language :: Python
Classifier: Programming Language :: Python :: 3
Classifier: Programming Language :: Python :: 3.7
Classifier: Programming Language :: Python :: 3.8
Classifier: Programming Language :: Python :: 3.9
Classifier: Programming Language :: Python :: 3.10
Classifier: License :: OSI Approved :: MIT License
Classifier: Topic :: Scientific/Engineering
Classifier: Topic :: Software Development
Classifier: Intended Audience :: Science/Research
Classifier: Intended Audience :: Developers
Provides-Extra: docs
Provides-Extra: dev
Provides-Extra: test
Provides-Extra: marine
License-File: LICENSE.md
